{"data":{"propertyOrder":{},"properties":{"dateDone":{"name":"dateDone","reference":"scalar","getter":false,"setter":false,"type":"Date","array":false},"name":{"name":"name","reference":"scalar","getter":false,"setter":false,"type":"string","array":false},"scrapQuantity":{"name":"scrapQuantity","reference":"scalar","getter":false,"setter":false,"type":"number","array":false},"state":{"name":"state","reference":"scalar","getter":false,"setter":false,"type":"string","array":false}},"props":[{"name":"dateDone","reference":"scalar","getter":false,"setter":false,"type":"Date","array":false},{"name":"name","reference":"scalar","getter":false,"setter":false,"type":"string","array":false},{"name":"scrapQuantity","reference":"scalar","getter":false,"setter":false,"type":"number","array":false},{"name":"state","reference":"scalar","getter":false,"setter":false,"type":"string","array":false}],"primaryKeys":[],"filters":{},"hooks":{},"indexes":[],"uniques":[],"concurrencyCheckKeys":{},"className":"ProductScrap","path":"./dist/inventory/inventory.entity.js","expression":"select ss.tanggal_kejadian date_done, pt.name, ss.scrap_qty, ss.state from stock_scrap ss, product_template pt where ss.product_id=pt.id","name":"ProductScrap","abstract":false,"constructorParams":[],"toJsonParams":[],"useCache":true,"relations":[],"collection":"product_scrap"},"origin":"./dist/inventory/inventory.entity.js","hash":"db48946fbbdce994ca0d9176c7d1e82e","version":"5.8.10"}
